whatsupbraeker-0.3.3.data/purelib/whatsupbraeker/__init__.py
whatsupbraeker-0.3.3.data/purelib/whatsupbraeker/lib/libwa.so
whatsupbraeker-0.3.3.dist-info/METADATA
whatsupbraeker-0.3.3.dist-info/WHEEL
whatsupbraeker-0.3.3.dist-info/top_level.txt
whatsupbraeker-0.3.3.dist-info/RECORD
