Metadata-Version: 2.4
Name: whatsupbraeker
Version: 0.3.3
Summary: Python bindings for the WhatsUpBraeker Go WhatsApp bridge.
License-Expression: LicenseRef-Proprietary
Keywords: whatsapp,whatsupbraeker,bridge
Classifier: Programming Language :: Python :: 3
Classifier: Programming Language :: Python :: 3 :: Only
Classifier: Programming Language :: Python :: Implementation :: CPython
Classifier: Operating System :: MacOS
Requires-Python: >=3.9
